server/__init__.py
server/app.py
vpf_730/__init__.py
vpf_730/__main__.py
vpf_730/logger.py
vpf_730/main.py
vpf_730/sender.py
vpf_730/utils.py
vpf_730/vpf_730.py
vpf_730-0.9.0.dist-info/LICENCE
vpf_730-0.9.0.dist-info/METADATA
vpf_730-0.9.0.dist-info/WHEEL
vpf_730-0.9.0.dist-info/entry_points.txt
vpf_730-0.9.0.dist-info/top_level.txt
vpf_730-0.9.0.dist-info/RECORD
