Metadata-Version: 2.1
Name: vpf-730
Version: 0.9.0
Summary: a library to read data from the Biral VPF-730 Present weather sensor
Home-page: https://github.com/RUB_Clim/vpf-730
Author: Jonas Kittner
Author-email: jonas.kittner@ruhr-uni-bochum.de
License: MIT
Classifier: License :: OSI Approved :: MIT License
Classifier: Programming Language :: Python :: 3
Classifier: Programming Language :: Python :: 3 :: Only
Classifier: Programming Language :: Python :: 3.8
Classifier: Programming Language :: Python :: 3.9
Classifier: Programming Language :: Python :: 3.10
Classifier: Programming Language :: Python :: 3.11
Classifier: Programming Language :: Python :: Implementation :: CPython
Requires-Python: >=3.9
License-File: LICENCE
Requires-Dist: pyserial
Requires-Dist: typing-extensions ; python_version < "3.10"
Provides-Extra: sentry
Requires-Dist: sentry-sdk ; extra == 'sentry'
